{
  "snappedPoints": [
    {
      "location": {
        "latitude": 26.6058766,
        "longitude": 106.64611819999999
      },
      "originalIndex": 0,
      "placeId": "ChIJ40QWMNlmvzYRvad8DDiBUoA"
    },
    {
      "location": {
        "latitude": 26.6055599,
        "longitude": 106.64616389999999
      },
      "placeId": "ChIJ40QWMNlmvzYRvad8DDiBUoA"
    },
    {
      "location": {
        "latitude": 26.6052515,
        "longitude": 106.6462056
      },
      "placeId": "ChIJ40QWMNlmvzYRvad8DDiBUoA"
    },
    {
      "location": {
        "latitude": 26.6052515,
        "longitude": 106.6462056
      },
      "placeId": "ChIJh16JSt9mvzYRXDJjNBf1VL0"
    },
    {
      "location": {
        "latitude": 26.604776200000003,
        "longitude": 106.6462701
      },
      "placeId": "ChIJh16JSt9mvzYRXDJjNBf1VL0"
    },
    {
      "location": {
        "latitude": 26.604496356658906,
        "longitude": 106.64633355138966
      },
      "originalIndex": 1,
      "placeId": "ChIJh16JSt9mvzYRXDJjNBf1VL0"
    },
    {
      "location": {
        "latitude": 26.604180799999998,
        "longitude": 106.6464051
      },
      "placeId": "ChIJh16JSt9mvzYRXDJjNBf1VL0"
    },
    {
      "location": {
        "latitude": 26.6036419,
        "longitude": 106.6465829
      },
      "placeId": "ChIJh16JSt9mvzYRXDJjNBf1VL0"
    },
    {
      "location": {
        "latitude": 26.603234990520647,
        "longitude": 106.64676147515397
      },
      "originalIndex": 2,
      "placeId": "ChIJh16JSt9mvzYRXDJjNBf1VL0"
    },
    {
      "location": {
        "latitude": 26.6030752,
        "longitude": 106.6468316
      },
      "placeId": "ChIJh16JSt9mvzYRXDJjNBf1VL0"
    },
    {
      "location": {
        "latitude": 26.6020415,
        "longitude": 106.6473921
      },
      "placeId": "ChIJh16JSt9mvzYRXDJjNBf1VL0"
    },
    {
      "location": {
        "latitude": 26.6015023,
        "longitude": 106.6477063
      },
      "placeId": "ChIJh16JSt9mvzYRXDJjNBf1VL0"
    },
    {
      "location": {
        "latitude": 26.6015023,
        "longitude": 106.6477063
      },
      "placeId": "ChIJFTBepiBnvzYRjyCapTe-qPY"
    },
    {
      "location": {
        "latitude": 26.601463225071853,
        "longitude": 106.64772906922823
      },
      "originalIndex": 3,
      "placeId": "ChIJFTBepiBnvzYRjyCapTe-qPY"
    },
    {
      "location": {
        "latitude": 26.6014491,
        "longitude": 106.6477373
      },
      "placeId": "ChIJFTBepiBnvzYRjyCapTe-qPY"
    },
    {
      "location": {
        "latitude": 26.6014491,
        "longitude": 106.6477373
      },
      "placeId": "ChIJPyKGpiBnvzYRvHScvZG6C1E"
    },
    {
      "location": {
        "latitude": 26.6013959,
        "longitude": 106.6477683
      },
      "placeId": "ChIJPyKGpiBnvzYRvHScvZG6C1E"
    },
    {
      "location": {
        "latitude": 26.6013959,
        "longitude": 106.6477683
      },
      "placeId": "ChIJeUPmvCBnvzYRO0g8F3R795s"
    },
    {
      "location": {
        "latitude": 26.600637000000003,
        "longitude": 106.64821099999999
      },
      "placeId": "ChIJeUPmvCBnvzYRO0g8F3R795s"
    },
    {
      "location": {
        "latitude": 26.600363400000003,
        "longitude": 106.6483635
      },
      "placeId": "ChIJeUPmvCBnvzYRO0g8F3R795s"
    },
    {
      "location": {
        "latitude": 26.600363400000003,
        "longitude": 106.6483635
      },
      "placeId": "ChIJr5cj7yBnvzYREPxlUCdrnAk"
    },
    {
      "location": {
        "latitude": 26.59993448614054,
        "longitude": 106.6486025343286
      },
      "originalIndex": 4,
      "placeId": "ChIJr5cj7yBnvzYREPxlUCdrnAk"
    },
    {
      "location": {
        "latitude": 26.599784000000007,
        "longitude": 106.64868639999999
      },
      "placeId": "ChIJr5cj7yBnvzYREPxlUCdrnAk"
    },
    {
      "location": {
        "latitude": 26.5994588,
        "longitude": 106.6488528
      },
      "placeId": "ChIJr5cj7yBnvzYREPxlUCdrnAk"
    },
    {
      "location": {
        "latitude": 26.5990163,
        "longitude": 106.64905309999999
      },
      "placeId": "ChIJr5cj7yBnvzYREPxlUCdrnAk"
    },
    {
      "location": {
        "latitude": 26.5988814,
        "longitude": 106.64909899999999
      },
      "placeId": "ChIJr5cj7yBnvzYREPxlUCdrnAk"
    },
    {
      "location": {
        "latitude": 26.5988814,
        "longitude": 106.64909899999999
      },
      "placeId": "ChIJdfIV_SBnvzYRkYZ0r3iBo_A"
    },
    {
      "location": {
        "latitude": 26.598756299999998,
        "longitude": 106.6491417
      },
      "placeId": "ChIJdfIV_SBnvzYRkYZ0r3iBo_A"
    },
    {
      "location": {
        "latitude": 26.598756299999998,
        "longitude": 106.6491417
      },
      "placeId": "ChIJE2JqcyFnvzYRmhS8fYo35KU"
    },
    {
      "location": {
        "latitude": 26.598536199999998,
        "longitude": 106.6492169
      },
      "placeId": "ChIJE2JqcyFnvzYRmhS8fYo35KU"
    },
    {
      "location": {
        "latitude": 26.598149837926517,
        "longitude": 106.64929221288463
      },
      "originalIndex": 5,
      "placeId": "ChIJE2JqcyFnvzYRmhS8fYo35KU"
    },
    {
      "location": {
        "latitude": 26.597858,
        "longitude": 106.6493491
      },
      "placeId": "ChIJE2JqcyFnvzYRmhS8fYo35KU"
    },
    {
      "location": {
        "latitude": 26.5973786,
        "longitude": 106.6494403
      },
      "placeId": "ChIJE2JqcyFnvzYRmhS8fYo35KU"
    },
    {
      "location": {
        "latitude": 26.5971089,
        "longitude": 106.64946909999999
      },
      "placeId": "ChIJE2JqcyFnvzYRmhS8fYo35KU"
    },
    {
      "location": {
        "latitude": 26.596857284214945,
        "longitude": 106.64947768920501
      },
      "originalIndex": 6,
      "placeId": "ChIJE2JqcyFnvzYRmhS8fYo35KU"
    },
    {
      "location": {
        "latitude": 26.5966314,
        "longitude": 106.64948539999999
      },
      "placeId": "ChIJE2JqcyFnvzYRmhS8fYo35KU"
    },
    {
      "location": {
        "latitude": 26.596254000000002,
        "longitude": 106.6494776
      },
      "placeId": "ChIJE2JqcyFnvzYRmhS8fYo35KU"
    },
    {
      "location": {
        "latitude": 26.5955723,
        "longitude": 106.6494027
      },
      "placeId": "ChIJE2JqcyFnvzYRmhS8fYo35KU"
    },
    {
      "location": {
        "latitude": 26.5955723,
        "longitude": 106.6494027
      },
      "placeId": "ChIJ7WF50SNnvzYRTXbINQiHM58"
    },
    {
      "location": {
        "latitude": 26.595453499999994,
        "longitude": 106.6493897
      },
      "placeId": "ChIJ7WF50SNnvzYRTXbINQiHM58"
    },
    {
      "location": {
        "latitude": 26.59539763228617,
        "longitude": 106.6493809562833
      },
      "originalIndex": 7,
      "placeId": "ChIJ7WF50SNnvzYRTXbINQiHM58"
    },
    {
      "location": {
        "latitude": 26.5950401,
        "longitude": 106.64932499999999
      },
      "placeId": "ChIJ7WF50SNnvzYRTXbINQiHM58"
    },
    {
      "location": {
        "latitude": 26.5950401,
        "longitude": 106.64932499999999
      },
      "placeId": "ChIJCUXAziNnvzYRdeiaLJYRlL8"
    },
    {
      "location": {
        "latitude": 26.594935999999997,
        "longitude": 106.6493101
      },
      "placeId": "ChIJCUXAziNnvzYRdeiaLJYRlL8"
    },
    {
      "location": {
        "latitude": 26.59469421215362,
        "longitude": 106.64927160999042
      },
      "originalIndex": 8,
      "placeId": "ChIJCUXAziNnvzYRdeiaLJYRlL8"
    }
  ]
}